deploifai/__init__.py
deploifai/cli/__init__.py
deploifai/cli/cli.py
deploifai/cli/context.py
deploifai/cli/api/__init__.py
deploifai/cli/api/errors.py
deploifai/cli/application/__init__.py
deploifai/cli/application/create.py
deploifai/cli/application/init.py
deploifai/cli/auth/__init__.py
deploifai/cli/auth/login.py
deploifai/cli/auth/logout.py
deploifai/cli/auth/status.py
deploifai/cli/cloud_profile/__init__.py
deploifai/cli/cloud_profile/create.py
deploifai/cli/cloud_profile/list.py
deploifai/cli/clouds/__init__.py
deploifai/cli/clouds/aws/__init__.py
deploifai/cli/clouds/aws/data_storage/__init__.py
deploifai/cli/clouds/aws/data_storage/handler.py
deploifai/cli/clouds/azure/__init__.py
deploifai/cli/clouds/azure/data_storage/__init__.py
deploifai/cli/clouds/azure/data_storage/handler.py
deploifai/cli/clouds/gcp/__init__.py
deploifai/cli/clouds/gcp/data_storage/__init__.py
deploifai/cli/clouds/gcp/data_storage/handler.py
deploifai/cli/clouds/utilities/__init__.py
deploifai/cli/clouds/utilities/data_storage/__init__.py
deploifai/cli/clouds/utilities/data_storage/handler.py
deploifai/cli/constants/__init__.py
deploifai/cli/core/__init__.py
deploifai/cli/core/data_storage/__init__.py
deploifai/cli/core/data_storage/data_storage.py
deploifai/cli/dataset/__init__.py
deploifai/cli/dataset/create.py
deploifai/cli/dataset/info.py
deploifai/cli/dataset/init.py
deploifai/cli/dataset/list.py
deploifai/cli/dataset/pull.py
deploifai/cli/dataset/push.py
deploifai/cli/experiment/__init__.py
deploifai/cli/experiment/create.py
deploifai/cli/mlflow/__init__.py
deploifai/cli/mlflow/get_setup.py
deploifai/cli/project/__init__.py
deploifai/cli/project/browse.py
deploifai/cli/project/create.py
deploifai/cli/project/info.py
deploifai/cli/project/init.py
deploifai/cli/project/list.py
deploifai/cli/server/__init__.py
deploifai/cli/server/create.py
deploifai/cli/server/list.py
deploifai/cli/server/start.py
deploifai/cli/server/stop.py
deploifai/cli/utilities/__init__.py
deploifai-0.4.3.dist-info/METADATA
deploifai-0.4.3.dist-info/WHEEL
deploifai-0.4.3.dist-info/entry_points.txt
deploifai-0.4.3.dist-info/top_level.txt
deploifai-0.4.3.dist-info/RECORD
