Metadata-Version: 2.1
Name: deploifai
Version: 0.4.3
Summary: Deploifai CLI
Home-page: https://github.com/deploifai/cli
Author: Deploifai Limited
Classifier: Programming Language :: Python :: 3.7
Classifier: Programming Language :: Python :: 3.8
Classifier: Programming Language :: Python :: 3.9
Classifier: Programming Language :: Python :: 3.10
Classifier: Operating System :: OS Independent
Requires-Python: >=3.7
Requires-Dist: click
Requires-Dist: python-dotenv
Requires-Dist: keyring
Requires-Dist: requests
Requires-Dist: click-spinner
Requires-Dist: tqdm
Requires-Dist: azure-identity
Requires-Dist: azure-storage-blob
Requires-Dist: boto3
Requires-Dist: google-auth
Requires-Dist: google-cloud-storage
Requires-Dist: docker
Requires-Dist: InquirerPy
Requires-Dist: pyperclip
Requires-Dist: semver
Requires-Dist: cryptography
